bioai_seq/__init__.py
bioai_seq/cli.py
bioai_seq/core/__init__.py
bioai_seq/core/db.py
bioai_seq/core/commands/__init__.py
bioai_seq/core/commands/analyze.py
bioai_seq/core/services/__init__.py
bioai_seq/core/services/chroma/__init__.py
bioai_seq/core/services/remote/__init__.py
bioai_seq/core/services/remote/find_metadata_by_id.py
bioai_seq/core/services/remote/get_embedding.py
bioai_seq-0.0.4.dist-info/licenses/LICENSE
bioai_seq-0.0.4.dist-info/METADATA
bioai_seq-0.0.4.dist-info/WHEEL
bioai_seq-0.0.4.dist-info/entry_points.txt
bioai_seq-0.0.4.dist-info/top_level.txt
bioai_seq-0.0.4.dist-info/RECORD
