Metadata-Version: 2.4
Name: bioai-seq
Version: 0.0.4
Summary: Privacy-first command-line tool for biotech devs and researchers to analyse sequence data.
Author-email: Jan Piotrzkowski <piotrzkowski.jan@gmail.com>
License: Apache-2.0
Classifier: Development Status :: 3 - Alpha
Classifier: Intended Audience :: Science/Research
Classifier: Topic :: Scientific/Engineering :: Bio-Informatics
Classifier: License :: OSI Approved :: Apache Software License
Classifier: Programming Language :: Python :: 3
Classifier: Programming Language :: Python :: 3.8
Classifier: Programming Language :: Python :: 3.9
Classifier: Programming Language :: Python :: 3.10
Classifier: Operating System :: OS Independent
Requires-Python: >=3.8
License-File: LICENSE
Requires-Dist: typer>=0.9.0
Requires-Dist: rich
Provides-Extra: esm
Requires-Dist: fair-esm; extra == "esm"
Dynamic: license-file
